odoo9_addon_account_partner_reconcile-9.0.1.0.0-py2.7-nspkg.pth
odoo9_addon_account_partner_reconcile-9.0.1.0.0.dist-info/DESCRIPTION.rst
odoo9_addon_account_partner_reconcile-9.0.1.0.0.dist-info/METADATA
odoo9_addon_account_partner_reconcile-9.0.1.0.0.dist-info/RECORD
odoo9_addon_account_partner_reconcile-9.0.1.0.0.dist-info/WHEEL
odoo9_addon_account_partner_reconcile-9.0.1.0.0.dist-info/metadata.json
odoo9_addon_account_partner_reconcile-9.0.1.0.0.dist-info/namespace_packages.txt
odoo9_addon_account_partner_reconcile-9.0.1.0.0.dist-info/top_level.txt
odoo_addons/account_partner_reconcile/README.rst
odoo_addons/account_partner_reconcile/__init__.py
odoo_addons/account_partner_reconcile/__openerp__.py
odoo_addons/account_partner_reconcile/models/__init__.py
odoo_addons/account_partner_reconcile/models/res_partner.py
odoo_addons/account_partner_reconcile/static/description/icon.png
odoo_addons/account_partner_reconcile/views/res_partner_view.xml
